cayman/__init__.py
cayman/__main__.py
cayman/functions.py
cayman/handle_args.py
cayman/annotate/__init__.py
cayman/annotate/crazy_annotator.py
cayman/bin/__init__.py
cayman-0.10.2.dist-info/licenses/LICENSE
cayman-0.10.2.dist-info/METADATA
cayman-0.10.2.dist-info/WHEEL
cayman-0.10.2.dist-info/entry_points.txt
cayman-0.10.2.dist-info/top_level.txt
cayman-0.10.2.dist-info/RECORD
