Metadata-Version: 2.4
Name: cayman
Version: 0.10.2
Home-page: https://github.com/zellerlab/cayman
Author: Christian Schudoma
Author-email: cschu1981@gmail.com
License: MIT
Classifier: Development Status :: 4 - Beta
Classifier: Topic :: Scientific/Engineering :: Bio-Informatics
Classifier: License :: OSI Approved :: MIT License
Classifier: Operating System :: POSIX :: Linux
Classifier: Programming Language :: Python :: 3.7
Classifier: Programming Language :: Python :: 3.8
Classifier: Programming Language :: Python :: 3.9
Classifier: Programming Language :: Python :: 3.10
License-File: LICENSE
Requires-Dist: numpy==1.24.2
Requires-Dist: pandas==1.5.3
Requires-Dist: pysam
Requires-Dist: gqlib>=2.14.3
Requires-Dist: pyhmmer
Dynamic: author
Dynamic: author-email
Dynamic: classifier
Dynamic: home-page
Dynamic: keywords
Dynamic: license
Dynamic: license-file
Dynamic: requires-dist
